app/__init__.py
app/config.py
app/main.py
app/models.py
app/monitor.py
app/api/__init__.py
app/api/health.py
app/ui/__init__.py
app/ui/docs.html
app/ui/index-simple.html
app/ui/index.html
app/ui/logo.png
glancewatch-1.2.3.dist-info/licenses/LICENSE
glancewatch-1.2.3.dist-info/METADATA
glancewatch-1.2.3.dist-info/WHEEL
glancewatch-1.2.3.dist-info/entry_points.txt
glancewatch-1.2.3.dist-info/top_level.txt
glancewatch-1.2.3.dist-info/RECORD
