Metadata-Version: 2.4
Name: glancewatch
Version: 1.2.3
Summary: Lightweight monitoring adapter bridging Glances metrics with Uptime Kuma
Author-email: Collins Kemboi <collynes@gmail.com>
License: MIT
Project-URL: Homepage, https://github.com/collynes/glancewatch
Project-URL: Documentation, https://github.com/collynes/glancewatch#readme
Project-URL: Repository, https://github.com/collynes/glancewatch
Project-URL: Issues, https://github.com/collynes/glancewatch/issues
Project-URL: Changelog, https://github.com/collynes/glancewatch/releases
Keywords: monitoring,glances,uptime-kuma,metrics,system-monitoring,server-monitoring
Classifier: Development Status :: 4 - Beta
Classifier: Intended Audience :: System Administrators
Classifier: License :: OSI Approved :: MIT License
Classifier: Programming Language :: Python :: 3
Classifier: Programming Language :: Python :: 3.8
Classifier: Programming Language :: Python :: 3.9
Classifier: Programming Language :: Python :: 3.10
Classifier: Programming Language :: Python :: 3.11
Classifier: Programming Language :: Python :: 3.12
Classifier: Topic :: System :: Monitoring
Classifier: Topic :: System :: Systems Administration
Classifier: Framework :: FastAPI
Requires-Python: >=3.8
License-File: LICENSE
Requires-Dist: fastapi>=0.109.0
Requires-Dist: uvicorn[standard]>=0.27.0
Requires-Dist: httpx>=0.26.0
Requires-Dist: pydantic>=2.5.0
Requires-Dist: pydantic-settings>=2.1.0
Requires-Dist: PyYAML>=6.0.1
Requires-Dist: glances>=3.4.0
Provides-Extra: dev
Requires-Dist: pytest>=7.4.0; extra == "dev"
Requires-Dist: pytest-asyncio>=0.21.0; extra == "dev"
Requires-Dist: pytest-cov>=4.1.0; extra == "dev"
Requires-Dist: black>=24.0.0; extra == "dev"
Requires-Dist: ruff>=0.1.0; extra == "dev"
Requires-Dist: mypy>=1.8.0; extra == "dev"
Requires-Dist: ipython>=8.18.0; extra == "dev"
Dynamic: license-file
